{
  "elements": [
    {
      "from": [
        0,
        0,
        14
      ],
      "to": [
        16,
        16,
        16
      ],
      "faces": {
        "down": {
          "texture": "#block",
          "cullface": "down"
        },
        "up": {
          "texture": "#block",
          "cullface": "up"
        },
        "north": {
          "texture": "#block"
        },
        "south": {
          "texture": "#block",
          "cullface": "south"
        },
        "west": {
          "texture": "#block",
          "cullface": "west"
        },
        "east": {
          "texture": "#block",
          "cullface": "east"
        }
      }
    }
  ]
}